Workbook

Sheet Assumptions
A1: Assumptions and Sources
A2: Blue cells are inputs. All tables reference them. Black cells are formulas.
A4: Financing
A5: 30-year fixed rate | B5: 0.0695 | C5: Freddie Mac PMMS, released 2026-09-17
A6: Loan term (months) | B6: 360 | C6: Standard 30-year term
A7: Housing DTI (front-end) | B7: 0.3 | C7: Per Sept 2026 NHS concept note
A8: Property tax rate | B8: 0.011 | C8: Per Sept 2026 NHS concept note
A9: Insurance (per month) | B9: 150 | C9: Per Sept 2026 NHS concept note
A10: Closing costs (% of price) | B10: 0.025 | C10: Estimate. Replace with NHS observed closing costs if available.
A11: FHA upfront MIP (financed) | B11: 0.0175 | C11: HUD, 2026
A13: LA County income limits, 4-person household
A14: Very low income | B14: 83300 | C14: HCD/HUD LA County, effective 2026-06-23
A15: Area median income | B15: 108100 | C15: HCD/HUD LA County, effective 2026-06-23
A16: Lower income (= moderate) | B16: 133250 | C16: HCD/HUD LA County. Lower and moderate limits are equal in 2026.
A18: Mortgage insurance, annual % of loan balance
A19: 97% LTV (3% down) | B19: 0.0121 | C19: Enact HFA rate card (effective 2018-06-04), 680-699 FICO baseline
A20: 95% LTV (5% down) | B20: 0.0096 | C20: Enact HFA rate card (effective 2018-06-04), 680-699 FICO baseline
A21: 90% LTV (10% down) | B21: 0.0065 | C21: Enact HFA rate card (effective 2018-06-04), 680-699 FICO baseline
A22: 80% LTV (20% down) | B22: 0 | C22: No mortgage insurance at 20% down
A23: FHA annual MIP | B23: 0.0055 | C23: HUD 2026, above 95% LTV. Continues for life of loan when down payment is under 10%.
A25: Compton price benchmark: Assessor base-year assessed values, 2025-26 transfers (proxy for sale price)
A26: 10th percentile | B26: 470766 | C26: LA County Assessor roll, pulled 2026-09-18
A27: 25th percentile | B27: 559482 | C27: LA County Assessor roll, pulled 2026-09-18
A28: Median | B28: 633926 | C28: LA County Assessor roll, pulled 2026-09-18
A29: 75th percentile | B29: 693600 | C29: LA County Assessor roll, pulled 2026-09-18
A30: 90th percentile | B30: 754086 | C30: LA County Assessor roll, pulled 2026-09-18
A31: Parcels in sample | B31: 746 | C31: Single-family, land and improvement base year both 2025 or 2026. Excludes 14 transfers under $200k.
A33: Percentile method: exclusive (Excel PERCENTILE.EXC) on the 746 retained parcels. The inclusive method gives a 25th percentile of about $559,985.

Sheet Purchasing Power
A1: Purchasing Power by Income Tier
A2: Maximum purchase price at the stated housing DTI. Includes principal, interest, property tax, insurance and mortgage insurance.
A4: Income tier | B4: 3% down (conventional 97) | C4: 3.5% down (FHA) | D4: 5% down (conventional 95) | E4: 10% down (conventional 90) | F4: 20% down (conventional 80)
A5: Down payment % | B5: 0.03 | C5: 0.035 | D5: 0.05 | E5: 0.1 | F5: 0.2
A6: Mortgage insurance rate | B6: =Assumptions!$B$19 -> 0.0121 | C6: =Assumptions!$B$23 -> 0.0055 | D6: =Assumptions!$B$20 -> 0.0096 | E6: =Assumptions!$B$21 -> 0.0065 | F6: =Assumptions!$B$22 -> 0
A7: Loan per $1 of price | B7: =1-B5 -> 0.97 | C7: =(1-C5)*(1+Assumptions!$B$11) -> 0.9818875 | D7: =1-D5 -> 0.95 | E7: =1-E5 -> 0.9 | F7: =1-F5 -> 0.8
A8: Maximum purchase price
A9: Very low income | B9: =(Assumptions!$B$14*Assumptions!$B$7/12-Assumptions!$B$9)/(B$7*(-PMT(Assumptions!$B$5/12,Assumptions!$B$6,1))+Assumptions!$B$8/12+B$7*B$6/12) -> 232393.29 | C9: =(Assumptions!$B$14*Assumptions!$B$7/12-Assumptions!$B$9)/(C$7*(-PMT(Assumptions!$B$5/12,Assumptions!$B$6,1))+Assumptions!$B$8/12+C$7*C$6/12) -> 245668.79 | D9: =(Assumptions!$B$14*Assumptions!$B$7/12-Assumptions!$B$9)/(D$7*(-PMT(Assumptions!$B$5/12,Assumptions!$B$6,1))+Assumptions!$B$8/12+D$7*D$6/12) -> 242618.75 | E9: =(Assumptions!$B$14*Assumptions!$B$7/12-Assumptions!$B$9)/(E$7*(-PMT(Assumptions!$B$5/12,Assumptions!$B$6,1))+Assumptions!$B$8/12+E$7*E$6/12) -> 262507.38 | F9: =(Assumptions!$B$14*Assumptions!$B$7/12-Assumptions!$B$9)/(F$7*(-PMT(Assumptions!$B$5/12,Assumptions!$B$6,1))+Assumptions!$B$8/12+F$7*F$6/12) -> 311078.92
A10: Area median income | B10: =(Assumptions!$B$15*Assumptions!$B$7/12-Assumptions!$B$9)/(B$7*(-PMT(Assumptions!$B$5/12,Assumptions!$B$6,1))+Assumptions!$B$8/12+B$7*B$6/12) -> 306951.55 | C10: =(Assumptions!$B$15*Assumptions!$B$7/12-Assumptions!$B$9)/(C$7*(-PMT(Assumptions!$B$5/12,Assumptions!$B$6,1))+Assumptions!$B$8/12+C$7*C$6/12) -> 324486.2 | D10: =(Assumptions!$B$15*Assumptions!$B$7/12-Assumptions!$B$9)/(D$7*(-PMT(Assumptions!$B$5/12,Assumptions!$B$6,1))+Assumptions!$B$8/12+D$7*D$6/12) -> 320457.62 | E10: =(Assumptions!$B$15*Assumptions!$B$7/12-Assumptions!$B$9)/(E$7*(-PMT(Assumptions!$B$5/12,Assumptions!$B$6,1))+Assumptions!$B$8/12+E$7*E$6/12) -> 346727.08 | F10: =(Assumptions!$B$15*Assumptions!$B$7/12-Assumptions!$B$9)/(F$7*(-PMT(Assumptions!$B$5/12,Assumptions!$B$6,1))+Assumptions!$B$8/12+F$7*F$6/12) -> 410881.73
A11: Lower income (= moderate) | B11: =(Assumptions!$B$16*Assumptions!$B$7/12-Assumptions!$B$9)/(B$7*(-PMT(Assumptions!$B$5/12,Assumptions!$B$6,1))+Assumptions!$B$8/12+B$7*B$6/12) -> 382562.04 | C11: =(Assumptions!$B$16*Assumptions!$B$7/12-Assumptions!$B$9)/(C$7*(-PMT(Assumptions!$B$5/12,Assumptions!$B$6,1))+Assumptions!$B$8/12+C$7*C$6/12) -> 404415.95 | D11: =(Assumptions!$B$16*Assumptions!$B$7/12-Assumptions!$B$9)/(D$7*(-PMT(Assumptions!$B$5/12,Assumptions!$B$6,1))+Assumptions!$B$8/12+D$7*D$6/12) -> 399395.03 | E11: =(Assumptions!$B$16*Assumptions!$B$7/12-Assumptions!$B$9)/(E$7*(-PMT(Assumptions!$B$5/12,Assumptions!$B$6,1))+Assumptions!$B$8/12+E$7*E$6/12) -> 432135.37 | F11: =(Assumptions!$B$16*Assumptions!$B$7/12-Assumptions!$B$9)/(F$7*(-PMT(Assumptions!$B$5/12,Assumptions!$B$6,1))+Assumptions!$B$8/12+F$7*F$6/12) -> 512093.05
A12: Gap to Compton median price (assessed-value proxy) | B12: =TEXT(Assumptions!$B$28,"$#,##0") -> $633,926
A13: Very low income | B13: =B9-Assumptions!$B$28 -> -401532.71 | C13: =C9-Assumptions!$B$28 -> -388257.21 | D13: =D9-Assumptions!$B$28 -> -391307.25 | E13: =E9-Assumptions!$B$28 -> -371418.62 | F13: =F9-Assumptions!$B$28 -> -322847.08
A14: Area median income | B14: =B10-Assumptions!$B$28 -> -326974.45 | C14: =C10-Assumptions!$B$28 -> -309439.8 | D14: =D10-Assumptions!$B$28 -> -313468.38 | E14: =E10-Assumptions!$B$28 -> -287198.92 | F14: =F10-Assumptions!$B$28 -> -223044.27
A15: Lower income (= moderate) | B15: =B11-Assumptions!$B$28 -> -251363.96 | C15: =C11-Assumptions!$B$28 -> -229510.05 | D15: =D11-Assumptions!$B$28 -> -234530.97 | E15: =E11-Assumptions!$B$28 -> -201790.63 | F15: =F11-Assumptions!$B$28 -> -121832.95

Sheet Cost to Buy
A1: Cost to Purchase
A2: Cash required, monthly cost and qualifying income at two price points.
A4: At the median price (assessed-value proxy) | B4: =Assumptions!$B$28 -> 633926
A5: Down payment | B5: Cash needed (down + closing) | C5: Loan amount | D5: Monthly PITI + MI | E5: Income required | F5: Monthly MI portion
A6: 3% down (conventional 97) | B6: =Assumptions!$B$28*0.03+Assumptions!$B$28*Assumptions!$B$10 -> 34865.93 | C6: =Assumptions!$B$28*(1-0.03) -> 614908.22 | D6: =C6*(-PMT(Assumptions!$B$5/12,Assumptions!$B$6,1))+Assumptions!$B$28*Assumptions!$B$8/12+Assumptions!$B$9+C6*Assumptions!$B$19/12 -> 5421.5034 | E6: =D6*12/Assumptions!$B$7 -> 216860.14 | F6: =C6*Assumptions!$B$19/12 -> 620.03246
A7: 3.5% down (FHA) | B7: =Assumptions!$B$28*0.035+Assumptions!$B$28*Assumptions!$B$10 -> 38035.56 | C7: =Assumptions!$B$28*(1-0.035)*(1+Assumptions!$B$11) -> 622444.02 | D7: =C7*(-PMT(Assumptions!$B$5/12,Assumptions!$B$6,1))+Assumptions!$B$28*Assumptions!$B$8/12+Assumptions!$B$9+C7*Assumptions!$B$23/12 -> 5136.6408 | E7: =D7*12/Assumptions!$B$7 -> 205465.63 | F7: =C7*Assumptions!$B$23/12 -> 285.28684
A8: 5% down (conventional 95) | B8: =Assumptions!$B$28*0.05+Assumptions!$B$28*Assumptions!$B$10 -> 47544.45 | C8: =Assumptions!$B$28*(1-0.05) -> 602229.7 | D8: =C8*(-PMT(Assumptions!$B$5/12,Assumptions!$B$6,1))+Assumptions!$B$28*Assumptions!$B$8/12+Assumptions!$B$9+C8*Assumptions!$B$20/12 -> 5199.3295 | E8: =D8*12/Assumptions!$B$7 -> 207973.18 | F8: =C8*Assumptions!$B$20/12 -> 481.78376
A9: 10% down (conventional 90) | B9: =Assumptions!$B$28*0.1+Assumptions!$B$28*Assumptions!$B$10 -> 79240.75 | C9: =Assumptions!$B$28*(1-0.1) -> 570533.4 | D9: =C9*(-PMT(Assumptions!$B$5/12,Assumptions!$B$6,1))+Assumptions!$B$28*Assumptions!$B$8/12+Assumptions!$B$9+C9*Assumptions!$B$21/12 -> 4816.7717 | E9: =D9*12/Assumptions!$B$7 -> 192670.87 | F9: =C9*Assumptions!$B$21/12 -> 309.03893
A10: 20% down (conventional 80) | B10: =Assumptions!$B$28*0.2+Assumptions!$B$28*Assumptions!$B$10 -> 142633.35 | C10: =Assumptions!$B$28*(1-0.2) -> 507140.8 | D10: =C10*(-PMT(Assumptions!$B$5/12,Assumptions!$B$6,1))+Assumptions!$B$28*Assumptions!$B$8/12+Assumptions!$B$9+C10*Assumptions!$B$22/12 -> 4088.1067 | E10: =D10*12/Assumptions!$B$7 -> 163524.27 | F10: =C10*Assumptions!$B$22/12 -> 0
A14: At the 25th-percentile price (assessed-value proxy) | B14: =Assumptions!$B$27 -> 559482
A15: Down payment | B15: Cash needed (down + closing) | C15: Loan amount | D15: Monthly PITI + MI | E15: Income required | F15: Monthly MI portion
A16: 3% down (conventional 97) | B16: =Assumptions!$B$27*0.03+Assumptions!$B$27*Assumptions!$B$10 -> 30771.51 | C16: =Assumptions!$B$27*(1-0.03) -> 542697.54 | D16: =C16*(-PMT(Assumptions!$B$5/12,Assumptions!$B$6,1))+Assumptions!$B$27*Assumptions!$B$8/12+Assumptions!$B$9+C16*Assumptions!$B$19/12 -> 4802.4535 | E16: =D16*12/Assumptions!$B$7 -> 192098.14 | F16: =C16*Assumptions!$B$19/12 -> 547.22002
A17: 3.5% down (FHA) | B17: =Assumptions!$B$27*0.035+Assumptions!$B$27*Assumptions!$B$10 -> 33568.92 | C17: =Assumptions!$B$27*(1-0.035)*(1+Assumptions!$B$11) -> 549348.38 | D17: =C17*(-PMT(Assumptions!$B$5/12,Assumptions!$B$6,1))+Assumptions!$B$27*Assumptions!$B$8/12+Assumptions!$B$9+C17*Assumptions!$B$23/12 -> 4551.0433 | E17: =D17*12/Assumptions!$B$7 -> 182041.73 | F17: =C17*Assumptions!$B$23/12 -> 251.78468
A18: 5% down (conventional 95) | B18: =Assumptions!$B$27*0.05+Assumptions!$B$27*Assumptions!$B$10 -> 41961.15 | C18: =Assumptions!$B$27*(1-0.05) -> 531507.9 | D18: =C18*(-PMT(Assumptions!$B$5/12,Assumptions!$B$6,1))+Assumptions!$B$27*Assumptions!$B$8/12+Assumptions!$B$9+C18*Assumptions!$B$20/12 -> 4606.3702 | E18: =D18*12/Assumptions!$B$7 -> 184254.81 | F18: =C18*Assumptions!$B$20/12 -> 425.20632
A19: 10% down (conventional 90) | B19: =Assumptions!$B$27*0.1+Assumptions!$B$27*Assumptions!$B$10 -> 69935.25 | C19: =Assumptions!$B$27*(1-0.1) -> 503533.8 | D19: =C19*(-PMT(Assumptions!$B$5/12,Assumptions!$B$6,1))+Assumptions!$B$27*Assumptions!$B$8/12+Assumptions!$B$9+C19*Assumptions!$B$21/12 -> 4268.7374 | E19: =D19*12/Assumptions!$B$7 -> 170749.5 | F19: =C19*Assumptions!$B$21/12 -> 272.74748
A20: 20% down (conventional 80) | B20: =Assumptions!$B$27*0.2+Assumptions!$B$27*Assumptions!$B$10 -> 125883.45 | C20: =Assumptions!$B$27*(1-0.2) -> 447585.6 | D20: =C20*(-PMT(Assumptions!$B$5/12,Assumptions!$B$6,1))+Assumptions!$B$27*Assumptions!$B$8/12+Assumptions!$B$9+C20*Assumptions!$B$22/12 -> 3625.642 | E20: =D20*12/Assumptions!$B$7 -> 145025.68 | F20: =C20*Assumptions!$B$22/12 -> 0
A24: FHA mortgage insurance continues for the life of the loan when the down payment is under 10%.

Sheet Assistance
A1: Down Payment Assistance Programs
A2: Verified September 2026. Amounts shown against Compton median price (assessed-value proxy).
A4: Program | B4: % of price | C4: Cap | D4: Amount available | E4: Available to a Compton buyer? | F4: Structure
A5: CalHFA MyHome (conventional) | B5: 0.03 | C5: none | D5: =Assumptions!$B$28*B5 -> 19017.78 | E5: Yes | F5: Deferred payment junior loan. Repayable, not a grant.
A6: CalHFA MyHome (FHA) | B6: 0.035 | C6: none | D6: =Assumptions!$B$28*B6 -> 22187.41 | E6: Yes | F6: Deferred payment junior loan. Repayable, not a grant.
A7: GSFA Platinum | B7: 0.055 | C7: none | D7: =Assumptions!$B$28*B7 -> 34865.93 | E7: Yes | F7: Gift plus second mortgage. No first-time buyer requirement.
A8: LACDA HOP80 | B8: 0.2 | C8: 100000 | D8: =MIN(Assumptions!$B$28*B8,C8) -> 100000 | E8: No. Compton is not a participating city. | F8: 0% deferred second with shared equity. Maximum purchase price $700,000.
A9: CalHFA Dream For All | B9: 0.2 | C9: 150000 | D9: =MIN(Assumptions!$B$28*B9,C9) -> 126785.2 | E9: No. Application window closed 2026-03-16. | F9: Shared appreciation loan. First-generation buyer requirement.
A13: Cash required after assistance, at median price
A14: Down payment | B14: Cash needed | C14: After CalHFA MyHome | D14: After GSFA Platinum
A15: 3% down (conventional 97) | B15: =Assumptions!$B$28*0.03+Assumptions!$B$28*Assumptions!$B$10 -> 34865.93 | C15: =MAX(0,B15-$D$5) -> 15848.15 | D15: =MAX(0,B15-$D$7) -> 0
A16: 3.5% down (FHA) | B16: =Assumptions!$B$28*0.035+Assumptions!$B$28*Assumptions!$B$10 -> 38035.56 | C16: =MAX(0,B16-$D$6) -> 15848.15 | D16: =MAX(0,B16-$D$7) -> 3169.63
A17: 5% down (conventional 95) | B17: =Assumptions!$B$28*0.05+Assumptions!$B$28*Assumptions!$B$10 -> 47544.45 | C17: =MAX(0,B17-$D$5) -> 28526.67 | D17: =MAX(0,B17-$D$7) -> 12678.52
A18: 10% down (conventional 90) | B18: =Assumptions!$B$28*0.1+Assumptions!$B$28*Assumptions!$B$10 -> 79240.75 | C18: =MAX(0,B18-$D$5) -> 60222.97 | D18: =MAX(0,B18-$D$7) -> 44374.82
A19: 20% down (conventional 80) | B19: =Assumptions!$B$28*0.2+Assumptions!$B$28*Assumptions!$B$10 -> 142633.35 | C19: =MAX(0,B19-$D$5) -> 123615.57 | D19: =MAX(0,B19-$D$7) -> 107767.42
A21: MyHome and GSFA Platinum attach to different first mortgages. They are alternatives, not additive. Confirm pairing rules with a participating lender.

Sheet Sensitivity
A1: Sensitivity
A2: Tested at 3% down.
A4: Housing DTI
A5: Front-end DTI | B5: Lower-income tier | C5: AMI tier | D5: Very low income tier
A6: 0.3 | B6: =(Assumptions!$B$16*A6/12-Assumptions!$B$9)/(0.97*(-PMT(Assumptions!$B$5/12,Assumptions!$B$6,1))+Assumptions!$B$8/12+0.97*Assumptions!$B$19/12) -> 382562.04 | C6: =(Assumptions!$B$15*A6/12-Assumptions!$B$9)/(0.97*(-PMT(Assumptions!$B$5/12,Assumptions!$B$6,1))+Assumptions!$B$8/12+0.97*Assumptions!$B$19/12) -> 306951.55 | D6: =(Assumptions!$B$14*A6/12-Assumptions!$B$9)/(0.97*(-PMT(Assumptions!$B$5/12,Assumptions!$B$6,1))+Assumptions!$B$8/12+0.97*Assumptions!$B$19/12) -> 232393.29
A7: 0.33 | B7: =(Assumptions!$B$16*A7/12-Assumptions!$B$9)/(0.97*(-PMT(Assumptions!$B$5/12,Assumptions!$B$6,1))+Assumptions!$B$8/12+0.97*Assumptions!$B$19/12) -> 422622.07 | C7: =(Assumptions!$B$15*A7/12-Assumptions!$B$9)/(0.97*(-PMT(Assumptions!$B$5/12,Assumptions!$B$6,1))+Assumptions!$B$8/12+0.97*Assumptions!$B$19/12) -> 339450.53 | D7: =(Assumptions!$B$14*A7/12-Assumptions!$B$9)/(0.97*(-PMT(Assumptions!$B$5/12,Assumptions!$B$6,1))+Assumptions!$B$8/12+0.97*Assumptions!$B$19/12) -> 257436.44
A8: 0.36 | B8: =(Assumptions!$B$16*A8/12-Assumptions!$B$9)/(0.97*(-PMT(Assumptions!$B$5/12,Assumptions!$B$6,1))+Assumptions!$B$8/12+0.97*Assumptions!$B$19/12) -> 462682.11 | C8: =(Assumptions!$B$15*A8/12-Assumptions!$B$9)/(0.97*(-PMT(Assumptions!$B$5/12,Assumptions!$B$6,1))+Assumptions!$B$8/12+0.97*Assumptions!$B$19/12) -> 371949.51 | D8: =(Assumptions!$B$14*A8/12-Assumptions!$B$9)/(0.97*(-PMT(Assumptions!$B$5/12,Assumptions!$B$6,1))+Assumptions!$B$8/12+0.97*Assumptions!$B$19/12) -> 282479.6
A11: Credit score, mortgage insurance pricing at 97% LTV
A12: FICO band | B12: PMI rate | C12: Monthly MI at median price | D12: Cost over 10 years
A13: 760+ | B13: 0.0058 | C13: =Assumptions!$B$28*0.97*B13/12 -> 297.20564 | D13: =C13*120 -> 35664.677
A14: 700-719 | B14: 0.0099 | C14: =Assumptions!$B$28*0.97*B14/12 -> 507.29928 | D14: =C14*120 -> 60875.914
A15: 680-699 (used above) | B15: 0.0121 | C15: =Assumptions!$B$28*0.97*B15/12 -> 620.03246 | D15: =C15*120 -> 74403.895
A16: 640-659 | B16: 0.0165 | C16: =Assumptions!$B$28*0.97*B16/12 -> 845.4988 | D16: =C16*120 -> 101459.86
A18: Source: Enact HFA rate card (effective 2018-06-04), fixed term over 20 years.
A20: Interest rate
A21: Rate | B21: Lower-income tier max price
A22: 0.0671 | B22: =(Assumptions!$B$16*Assumptions!$B$7/12-Assumptions!$B$9)/(0.97*(-PMT(A22/12,Assumptions!$B$6,1))+Assumptions!$B$8/12+0.97*Assumptions!$B$19/12) -> 389840.82 | C22: Concept note, 2026-09-03
A23: 0.0695 | B23: =(Assumptions!$B$16*Assumptions!$B$7/12-Assumptions!$B$9)/(0.97*(-PMT(A23/12,Assumptions!$B$6,1))+Assumptions!$B$8/12+0.97*Assumptions!$B$19/12) -> 382562.04 | C23: Current, 2026-09-17
A24: Difference | B24: =B22-B23 -> 7278.779
A25: Figures shared externally should carry the rate date.
